{
  "animateLoading": true,
  "borderRadius": "{{appsmith.theme.borderRadius.appBorderRadius}}",
  "bottomRow": 14,
  "dynamicBindingPathList": [
    {
      "key": "truncateButtonColor"
    },
    {
      "key": "fontFamily"
    },
    {
      "key": "borderRadius"
    },
    {
      "key": "text"
    }
  ],
  "dynamicHeight": "AUTO_HEIGHT",
  "dynamicTriggerPathList": [],
  "fontFamily": "{{appsmith.theme.fontFamily.appFont}}",
  "fontSize": "0.875rem",
  "fontStyle": "BOLD",
  "isLoading": false,
  "isVisible": true,
  "key": "dxf2xsi03o",
  "leftColumn": 1,
  "maxDynamicHeight": 9000,
  "minDynamicHeight": 4,
  "minWidth": 450,
  "mobileBottomRow": 9,
  "mobileLeftColumn": 5,
  "mobileRightColumn": 21,
  "mobileTopRow": 5,
  "needsErrorInfo": false,
  "originalBottomRow": 15,
  "originalTopRow": 10,
  "overflow": "NONE",
  "parentColumnSpace": 4.28125,
  "parentId": "vw3450n4lm",
  "parentRowSpace": 10,
  "renderMode": "CANVAS",
  "responsiveBehavior": "fill",
  "rightColumn": 44,
  "shouldTruncate": false,
  "text": "↗ +{{DynamicData.getKPIData().salesChange}}% vs last period",
  "textAlign": "LEFT",
  "textColor": "#00a047",
  "topRow": 10,
  "truncateButtonColor": "{{appsmith.theme.colors.primaryColor}}",
  "type": "TEXT_WIDGET",
  "version": 1,
  "widgetId": "17j06dfgyr",
  "widgetName": "TotalSalesobject"
}